{
  "squad": [
    {
      "player_id": 736,
      "full_name": "Gianluigi Donnarumma",
      "team_name": "Man City",
      "team_id": 13,
      "element_type": 1,
      "now_cost_millions": 5.7,
      "expected_points": 6.5907350296542155,
      "starting": 1,
      "bench": 0,
      "captain": 0,
      "next_fixture": "NEW (A)"
    },
    {
      "player_id": 110,
      "full_name": "Michael Kayode",
      "team_name": "Brentford",
      "team_id": 5,
      "element_type": 2,
      "now_cost_millions": 4.5,
      "expected_points": 6.929328389934064,
      "starting": 1,
      "bench": 0,
      "captain": 1,
      "next_fixture": "BHA (A)"
    },
    {
      "player_id": 5,
      "full_name": "Gabriel dos Santos Magalh\u00e3es",
      "team_name": "Arsenal",
      "team_id": 1,
      "element_type": 2,
      "now_cost_millions": 6.4,
      "expected_points": 4.918613018274022,
      "starting": 1,
      "bench": 0,
      "captain": 0,
      "next_fixture": "TOT (H)"
    },
    {
      "player_id": 6,
      "full_name": "William Saliba",
      "team_name": "Arsenal",
      "team_id": 1,
      "element_type": 2,
      "now_cost_millions": 6.0,
      "expected_points": 4.909628979629486,
      "starting": 1,
      "bench": 0,
      "captain": 0,
      "next_fixture": "TOT (H)"
    },
    {
      "player_id": 233,
      "full_name": "Josh Acheampong",
      "team_name": "Chelsea",
      "team_id": 7,
      "element_type": 2,
      "now_cost_millions": 3.9,
      "expected_points": 4.347462980435352,
      "starting": 1,
      "bench": 0,
      "captain": 0,
      "next_fixture": "BUR (A)"
    },
    {
      "player_id": 302,
      "full_name": "Idrissa Gana Gueye",
      "team_name": "Everton",
      "team_id": 9,
      "element_type": 3,
      "now_cost_millions": 5.4,
      "expected_points": 5.320046574587139,
      "starting": 1,
      "bench": 0,
      "captain": 0,
      "next_fixture": "MUN (A)"
    },
    {
      "player_id": 267,
      "full_name": "Isma\u00efla Sarr",
      "team_name": "Crystal Palace",
      "team_id": 8,
      "element_type": 3,
      "now_cost_millions": 6.5,
      "expected_points": 5.097729801184878,
      "starting": 1,
      "bench": 0,
      "captain": 0,
      "next_fixture": "WOL (A)"
    },
    {
      "player_id": 19,
      "full_name": "Gabriel Martinelli Silva",
      "team_name": "Arsenal",
      "team_id": 1,
      "element_type": 3,
      "now_cost_millions": 6.9,
      "expected_points": 4.430221447619321,
      "starting": 1,
      "bench": 0,
      "captain": 0,
      "next_fixture": "TOT (H)"
    },
    {
      "player_id": 491,
      "full_name": "Sandro Tonali",
      "team_name": "Newcastle",
      "team_id": 15,
      "element_type": 3,
      "now_cost_millions": 5.4,
      "expected_points": 4.339447624499712,
      "starting": 1,
      "bench": 0,
      "captain": 0,
      "next_fixture": "MCI (H)"
    },
    {
      "player_id": 430,
      "full_name": "Erling Haaland",
      "team_name": "Man City",
      "team_id": 13,
      "element_type": 4,
      "now_cost_millions": 14.7,
      "expected_points": 6.39858543388571,
      "starting": 1,
      "bench": 0,
      "captain": 0,
      "next_fixture": "NEW (A)"
    },
    {
      "player_id": 661,
      "full_name": "Hugo Ekitik\u00e9",
      "team_name": "Liverpool",
      "team_id": 12,
      "element_type": 4,
      "now_cost_millions": 8.7,
      "expected_points": 4.225882289010437,
      "starting": 1,
      "bench": 0,
      "captain": 0,
      "next_fixture": "NFO (H)"
    }
  ],
  "bench": [
    {
      "player_id": 258,
      "full_name": "Tyrick Mitchell",
      "team_name": "Crystal Palace",
      "team_id": 8,
      "element_type": 2,
      "now_cost_millions": 5.0,
      "expected_points": 4.775108205936267,
      "starting": 0,
      "bench": 1,
      "captain": 0,
      "bench_order": 1,
      "next_fixture": "WOL (A)"
    },
    {
      "player_id": 328,
      "full_name": "Ryan Sessegnon",
      "team_name": "Fulham",
      "team_id": 10,
      "element_type": 3,
      "now_cost_millions": 5.4,
      "expected_points": 4.211864745634944,
      "starting": 0,
      "bench": 1,
      "captain": 0,
      "bench_order": 2,
      "next_fixture": "SUN (H)"
    },
    {
      "player_id": 283,
      "full_name": "Jean-Philippe Mateta",
      "team_name": "Crystal Palace",
      "team_id": 8,
      "element_type": 4,
      "now_cost_millions": 7.6,
      "expected_points": 3.647636506625303,
      "starting": 0,
      "bench": 1,
      "captain": 0,
      "bench_order": 3,
      "next_fixture": "WOL (A)"
    },
    {
      "player_id": 142,
      "full_name": "Kjell Scherpen",
      "team_name": "Brighton",
      "team_id": 6,
      "element_type": 1,
      "now_cost_millions": 4.0,
      "expected_points": 3.5830046262204522,
      "starting": 0,
      "bench": 1,
      "captain": 0,
      "bench_order": 4,
      "next_fixture": "BRE (H)"
    }
  ],
  "total_cost": 96.10000000000001,
  "starting_cost": 74.10000000000001,
  "bench_cost": 22.0,
  "expected_points_without_captain": 57.50768156871434,
  "total_expected_points_with_captain": 64.4370099586484,
  "bench_expected_points": 16.217614084416965,
  "captain": "Michael Kayode",
  "formation": {
    "GK": 1,
    "DEF": 4,
    "MID": 4,
    "FWD": 2
  },
  "formation_name": "4-4-2"
}